cleanstring/__init__.py
cleanstring/serviceAccountKey.json
cleanstring/str_utils.py
cleanstring-0.2.2.dist-info/LICENSE
cleanstring-0.2.2.dist-info/METADATA
cleanstring-0.2.2.dist-info/WHEEL
cleanstring-0.2.2.dist-info/top_level.txt
cleanstring-0.2.2.dist-info/RECORD
