Metadata-Version: 2.1
Name: cleanstring
Version: 0.2.2
Summary: A simple package to clean strings
Home-page: https://github.com/yourusername/cleanstring
Author: Your Name
Author-email: coolmurdock6@justzeus.com
Classifier: Programming Language :: Python :: 3
Classifier: License :: OSI Approved :: MIT License
Classifier: Operating System :: OS Independent
Requires-Python: >=3.6
License-File: LICENSE
Requires-Dist: firebase-admin
